pyandon/__init__.py
pyandon/test.py
pyandon/drivers/__init__.py
pyandon/drivers/andon_driver.py
pyandon/drivers/andon_usb_driver.py
pyandon/drivers/patlite.py
pyandon/drivers/types.py
pyandon-0.1.2.dist-info/LICENSE
pyandon-0.1.2.dist-info/METADATA
pyandon-0.1.2.dist-info/WHEEL
pyandon-0.1.2.dist-info/top_level.txt
pyandon-0.1.2.dist-info/RECORD
