Metadata-Version: 2.1
Name: pyandon
Version: 0.1.2
Summary: Python module for interacting with a range of different andon light systems
Home-page: https://github.com/metislabs/pyandon
Author: Mike Sheldon
Author-email: mike.sheldon@metislabs.tech
License: MIT
Keywords: andon light warning patlite buzzer
Platform: UNKNOWN
Classifier: Development Status :: 3 - Alpha
Classifier: Intended Audience :: Manufacturing
Classifier: Topic :: System :: Hardware :: Hardware Drivers
Classifier: License :: OSI Approved :: MIT License
Classifier: Programming Language :: Python :: 3
Requires-Dist: pyusb
